astroimages_file_drivers/__init__.py
astroimages_file_drivers/driver.py
astroimages_file_drivers/factory.py
astroimages_file_drivers/handler_enums.py
astroimages_file_drivers/drivers/__init__.py
astroimages_file_drivers/drivers/local_file_driver.py
astroimages_file_drivers/drivers/minio_file_driver.py
astroimages_file_drivers/drivers/null_file_driver.py
astroimages_file_drivers/drivers/s3_file_driver.py
astroimages_file_drivers/util/__init__.py
astroimages_file_drivers/util/local_file_system.py
astroimages_file_drivers-0.1.6.dist-info/LICENSE
astroimages_file_drivers-0.1.6.dist-info/METADATA
astroimages_file_drivers-0.1.6.dist-info/WHEEL
astroimages_file_drivers-0.1.6.dist-info/top_level.txt
astroimages_file_drivers-0.1.6.dist-info/RECORD
