Metadata-Version: 2.1
Name: astroimages-file-drivers
Version: 0.1.6
Summary: File handling routines
Home-page: https://github.com/AstroImages/astroimages-file-drivers
Author: Rodrigo de Souza
Author-email: rsouza01@gmail.com
License: MIT License
